[
  {
    "image": "/additions/artists_imgs/17078289928187.jpg",
    "songName": "נשבע",
    "artist": "חיים משה",
    "href": "https://tab4u.com/tabs/songs/1500_%D7%97%D7%99%D7%99%D7%9D_%D7%9E%D7%A9%D7%94_-_%D7%A0%D7%A9%D7%91%D7%A2.html"
  },
  {
    "image": "/images/noArtPicDu.svg",
    "songName": "לא בוגד",
    "artist": "שימי מזרחי",
    "href": "https://tab4u.com/tabs/songs/5575_%D7%A9%D7%99%D7%9E%D7%99_%D7%9E%D7%96%D7%A8%D7%97%D7%99_-_%D7%9C%D7%90_%D7%91%D7%95%D7%92%D7%93.html"
  },
  {
    "image": "/additions/artists_imgs/17082702644006.jpg",
    "songName": "נשבע לך",
    "artist": "משה פרץ",
    "href": "https://tab4u.com/tabs/songs/4326_%D7%9E%D7%A9%D7%94_%D7%A4%D7%A8%D7%A5_-_%D7%A0%D7%A9%D7%91%D7%A2_%D7%9C%D7%9A.html"
  },
  {
    "image": "/additions/artists_imgs/Regev-Hod.gif",
    "songName": "נשבענו",
    "artist": "רגב הוד",
    "href": "https://tab4u.com/tabs/songs/4285_%D7%A8%D7%92%D7%91_%D7%94%D7%95%D7%93_-_%D7%A0%D7%A9%D7%91%D7%A2%D7%A0%D7%95.html"
  },
  {
    "image": "/images/noArtPicDu.svg",
    "songName": "נשבעתי לחזור אליך",
    "artist": "ליילי",
    "href": "https://tab4u.com/tabs/songs/67192_%D7%9C%D7%99%D7%99%D7%9C%D7%99_-_%D7%A0%D7%A9%D7%91%D7%A2%D7%AA%D7%99_%D7%9C%D7%97%D7%96%D7%95%D7%A8_%D7%90%D7%9C%D7%99%D7%9A.html"
  },
  {
    "image": "/additions/artists_imgs/1708269725867.jpg",
    "songName": "נשבעתי לך",
    "artist": "אריק סיני ויוני גנוט",
    "href": "https://tab4u.com/tabs/songs/71970_%D7%90%D7%A8%D7%99%D7%A7_%D7%A1%D7%99%D7%A0%D7%99_%D7%95%D7%99%D7%95%D7%A0%D7%99_%D7%92%D7%A0%D7%95%D7%98_-_%D7%A0%D7%A9%D7%91%D7%A2%D7%AA%D7%99_%D7%9C%D7%9A.html"
  },
  {
    "image": "/additions/artists_imgs/15328630634786.jpg",
    "songName": "לא נשבע סתם",
    "artist": "כוכב אניס",
    "href": "https://tab4u.com/tabs/songs/8503_%D7%9B%D7%95%D7%9B%D7%91_%D7%90%D7%A0%D7%99%D7%A1_-_%D7%9C%D7%90_%D7%A0%D7%A9%D7%91%D7%A2_%D7%A1%D7%AA%D7%9D.html"
  },
  {
    "image": "/additions/artists_imgs/eyal_golan.jpg",
    "songName": "נשבע לך כאן",
    "artist": "אייל גולן",
    "href": "https://tab4u.com/tabs/songs/67580_%D7%90%D7%99%D7%99%D7%9C_%D7%92%D7%95%D7%9C%D7%9F_-_%D7%A0%D7%A9%D7%91%D7%A2_%D7%9C%D7%9A_%D7%9B%D7%90%D7%9F.html"
  },
  {
    "image": "/additions/artists_imgs/eyal_golan.jpg",
    "songName": "נשבע לך כאן",
    "artist": "אייל גולן",
    "href": "https://tab4u.com/tabs/songs/67539_%D7%90%D7%99%D7%99%D7%9C_%D7%92%D7%95%D7%9C%D7%9F_-_%D7%A0%D7%A9%D7%91%D7%A2_%D7%9C%D7%9A_%D7%9B%D7%90%D7%9F.html"
  }
]